curl2/__init__.py
curl2/__version__.py
curl2/curl.py
curl2/run.py
curl2-1.1.2.dist-info/LICENSE
curl2-1.1.2.dist-info/METADATA
curl2-1.1.2.dist-info/WHEEL
curl2-1.1.2.dist-info/entry_points.txt
curl2-1.1.2.dist-info/top_level.txt
curl2-1.1.2.dist-info/RECORD
