Metadata-Version: 2.1
Name: curl2
Version: 1.1.2
Summary: cURL To Lang
Home-page: https://leesoar.com
Author: leesoar
Author-email: secure@tom.com
License: MIT
Platform: UNKNOWN
Classifier: License :: OSI Approved :: MIT License
Classifier: Programming Language :: Python :: 3.5
Classifier: Programming Language :: Python :: 3.6
Classifier: Programming Language :: Python :: 3.7
Classifier: Programming Language :: Python :: Implementation :: CPython
Classifier: Programming Language :: Python :: Implementation :: PyPy
Requires-Python: >=3.5.0
Requires-Dist: PyExecJS (==1.5.1)
Requires-Dist: six (==1.14.0)
